<?xml version='1.0' encoding='utf-8'?>
<tv><programme start="20250411000000 +0100" stop="20250411040000 +0100" channel="radionostalgie"><title lang="fr">Pas de programme</title></programme><programme start="20250411040000 +0100" stop="20250411060000 +0100" channel="radionostalgie"><title lang="fr">C'est pas trop tôt</title></programme><programme start="20250411060000 +0100" stop="20250411090000 +0100" channel="radionostalgie"><title lang="fr">La Nostra Family</title></programme><programme start="20250411090000 +0100" stop="20250411100000 +0100" channel="radionostalgie"><title lang="fr">Mission Nostraman</title></programme><programme start="20250411100000 +0100" stop="20250411130000 +0100" channel="radionostalgie"><title lang="fr">Le 10-13</title></programme><programme start="20250411130000 +0100" stop="20250411160000 +0100" channel="radionostalgie"><title lang="fr">Le 13-16</title></programme><programme start="20250411160000 +0100" stop="20250411200000 +0100" channel="radionostalgie"><title lang="fr">Le 16-20</title></programme><programme start="20250411200000 +0100" stop="20250411000000 +0100" channel="radionostalgie"><title lang="fr">Le Nostra Club</title></programme><programme start="20250412000000 +0100" stop="20250412040000 +0100" channel="radionostalgie"><title lang="fr">Pas de programme</title></programme><programme start="20250412040000 +0100" stop="20250412060000 +0100" channel="radionostalgie"><title lang="fr">C'est pas trop tôt</title></programme><programme start="20250412060000 +0100" stop="20250412090000 +0100" channel="radionostalgie"><title lang="fr">La Nostra Family</title></programme><programme start="20250412090000 +0100" stop="20250412100000 +0100" channel="radionostalgie"><title lang="fr">Mission Nostraman</title></programme><programme start="20250412100000 +0100" stop="20250412130000 +0100" channel="radionostalgie"><title lang="fr">Le 10-13</title></programme><programme start="20250412130000 +0100" stop="20250412160000 +0100" channel="radionostalgie"><title lang="fr">Le 13-16</title></programme><programme start="20250412160000 +0100" stop="20250412200000 +0100" channel="radionostalgie"><title lang="fr">Le 16-20</title></programme><programme start="20250412200000 +0100" stop="20250412000000 +0100" channel="radionostalgie"><title lang="fr">Le Nostra Club</title></programme><programme start="20250413000000 +0100" stop="20250413040000 +0100" channel="radionostalgie"><title lang="fr">Pas de programme</title></programme><programme start="20250413040000 +0100" stop="20250413060000 +0100" channel="radionostalgie"><title lang="fr">C'est pas trop tôt</title></programme><programme start="20250413060000 +0100" stop="20250413090000 +0100" channel="radionostalgie"><title lang="fr">La Nostra Family</title></programme><programme start="20250413090000 +0100" stop="20250413100000 +0100" channel="radionostalgie"><title lang="fr">Mission Nostraman</title></programme><programme start="20250413100000 +0100" stop="20250413130000 +0100" channel="radionostalgie"><title lang="fr">Le 10-13</title></programme><programme start="20250413130000 +0100" stop="20250413160000 +0100" channel="radionostalgie"><title lang="fr">Le 13-16</title></programme><programme start="20250413160000 +0100" stop="20250413200000 +0100" channel="radionostalgie"><title lang="fr">Le 16-20</title></programme><programme start="20250413200000 +0100" stop="20250413000000 +0100" channel="radionostalgie"><title lang="fr">Le Nostra Club</title></programme><programme start="20250414000000 +0100" stop="20250414040000 +0100" channel="radionostalgie"><title lang="fr">Pas de programme</title></programme><programme start="20250414040000 +0100" stop="20250414060000 +0100" channel="radionostalgie"><title lang="fr">C'est pas trop tôt</title></programme><programme start="20250414060000 +0100" stop="20250414090000 +0100" channel="radionostalgie"><title lang="fr">La Nostra Family</title></programme><programme start="20250414090000 +0100" stop="20250414100000 +0100" channel="radionostalgie"><title lang="fr">Mission Nostraman</title></programme><programme start="20250414100000 +0100" stop="20250414130000 +0100" channel="radionostalgie"><title lang="fr">Le 10-13</title></programme><programme start="20250414130000 +0100" stop="20250414160000 +0100" channel="radionostalgie"><title lang="fr">Le 13-16</title></programme><programme start="20250414160000 +0100" stop="20250414200000 +0100" channel="radionostalgie"><title lang="fr">Le 16-20</title></programme><programme start="20250414200000 +0100" stop="20250414000000 +0100" channel="radionostalgie"><title lang="fr">Le Nostra Club</title></programme><programme start="20250415000000 +0100" stop="20250415040000 +0100" channel="radionostalgie"><title lang="fr">Pas de programme</title></programme><programme start="20250415040000 +0100" stop="20250415060000 +0100" channel="radionostalgie"><title lang="fr">C'est pas trop tôt</title></programme><programme start="20250415060000 +0100" stop="20250415090000 +0100" channel="radionostalgie"><title lang="fr">La Nostra Family</title></programme><programme start="20250415090000 +0100" stop="20250415100000 +0100" channel="radionostalgie"><title lang="fr">Mission Nostraman</title></programme><programme start="20250415100000 +0100" stop="20250415130000 +0100" channel="radionostalgie"><title lang="fr">Le 10-13</title></programme><programme start="20250415130000 +0100" stop="20250415160000 +0100" channel="radionostalgie"><title lang="fr">Le 13-16</title></programme><programme start="20250415160000 +0100" stop="20250415200000 +0100" channel="radionostalgie"><title lang="fr">Le 16-20</title></programme><programme start="20250415200000 +0100" stop="20250415000000 +0100" channel="radionostalgie"><title lang="fr">Le Nostra Club</title></programme><programme start="20250416000000 +0100" stop="20250416060000 +0100" channel="radionostalgie"><title lang="fr">Pas de programme</title></programme><programme start="20250416060000 +0100" stop="20250416090000 +0100" channel="radionostalgie"><title lang="fr">La Nostra Family du Week-end</title></programme><programme start="20250416090000 +0100" stop="20250416100000 +0100" channel="radionostalgie"><title lang="fr">Le meilleur de Nostalgie</title></programme><programme start="20250416100000 +0100" stop="20250416120000 +0100" channel="radionostalgie"><title lang="fr">120 Minutes en ...</title></programme><programme start="20250416150000 +0100" stop="20250416180000 +0100" channel="radionostalgie"><title lang="fr">Le 15-18</title></programme><programme start="20250416180000 +0100" stop="20250416200000 +0100" channel="radionostalgie"><title lang="fr">Nostalgie In The Mix</title></programme><programme start="20250416200000 +0100" stop="20250416000000 +0100" channel="radionostalgie"><title lang="fr">Nostalgie SoulParty</title></programme><programme start="20250417000000 +0100" stop="20250417060000 +0100" channel="radionostalgie"><title lang="fr">Pas de programme</title></programme><programme start="20250417060000 +0100" stop="20250417090000 +0100" channel="radionostalgie"><title lang="fr">La Nostra Family du Week-end</title></programme><programme start="20250417090000 +0100" stop="20250417100000 +0100" channel="radionostalgie"><title lang="fr">La Musique de Nostalgie+</title></programme><programme start="20250417100000 +0100" stop="20250417120000 +0100" channel="radionostalgie"><title lang="fr">120 Minutes en ...</title></programme><programme start="20250417150000 +0100" stop="20250417180000 +0100" channel="radionostalgie"><title lang="fr">Le 15-18</title></programme><programme start="20250417180000 +0100" stop="20250417200000 +0100" channel="radionostalgie"><title lang="fr">Nostalgie 2000</title></programme><programme start="20250417200000 +0100" stop="20250417000000 +0100" channel="radionostalgie"><title lang="fr">Nostalgie Love</title></programme></tv>