<tv><programme start="20260407201500 +0100" stop="20260408141400 +0100" channel="rtlinfo"><title lang="fr">RTL info 19h. 07/04/2026</title></programme><programme start="20260408141500 +0100" stop="20260408201400 +0100" channel="rtlinfo"><title lang="fr">RTL info 13h. 08/04/2026</title></programme><programme start="20260408201500 +0100" stop="20260409141400 +0100" channel="rtlinfo"><title lang="fr">RTL info 19h. 08/04/2026</title></programme><programme start="20260409141500 +0100" stop="20260409201400 +0100" channel="rtlinfo"><title lang="fr">RTL info 13h. 09/04/2026</title></programme><programme start="20260409201500 +0100" stop="20260410141400 +0100" channel="rtlinfo"><title lang="fr">RTL info 19h. 09/04/2026</title></programme></tv>