<tv><programme start="20250228201500 +0100" stop="20250301141400 +0100" channel="rtlinfo"><title lang="fr">RTL info 19h. 28/02/2025</title></programme><programme start="20250301141500 +0100" stop="20250301201400 +0100" channel="rtlinfo"><title lang="fr">RTL info 13h. 01/03/2025</title></programme><programme start="20250301201500 +0100" stop="20250302141400 +0100" channel="rtlinfo"><title lang="fr">RTL info 19h. 01/03/2025</title></programme><programme start="20250302141500 +0100" stop="20250302201400 +0100" channel="rtlinfo"><title lang="fr">RTL info 13h. 02/03/2025</title></programme><programme start="20250302201500 +0100" stop="20250303141400 +0100" channel="rtlinfo"><title lang="fr">RTL info 19h. 02/03/2025</title></programme></tv>