<tv><programme start="20260428201500 +0100" stop="20260429141400 +0100" channel="rtlinfo"><title lang="fr">RTL info 19h. 28/04/2026</title></programme><programme start="20260429141500 +0100" stop="20260429201400 +0100" channel="rtlinfo"><title lang="fr">RTL info 13h. 29/04/2026</title></programme><programme start="20260429201500 +0100" stop="20260430141400 +0100" channel="rtlinfo"><title lang="fr">RTL info 19h. 29/04/2026</title></programme><programme start="20260430141500 +0100" stop="20260430201400 +0100" channel="rtlinfo"><title lang="fr">RTL info 13h. 30/04/2026</title></programme><programme start="20260430201500 +0100" stop="20260501141400 +0100" channel="rtlinfo"><title lang="fr">RTL info 19h. 30/04/2026</title></programme></tv>